nonebot_plugin_yuefu/__init__.py
nonebot_plugin_yuefu/config.py
nonebot_plugin_yuefu-0.1.1.dist-info/LICENSE
nonebot_plugin_yuefu-0.1.1.dist-info/METADATA
nonebot_plugin_yuefu-0.1.1.dist-info/WHEEL
nonebot_plugin_yuefu-0.1.1.dist-info/RECORD
