Metadata-Version: 2.1
Name: nonebot-plugin-yuefu
Version: 0.1.1
Summary: AI乐府Nonebot插件
Author: Chengzhi
Author-email: zmq175@qq.com
Requires-Python: >=3.9,<4.0
Classifier: Programming Language :: Python :: 3
Classifier: Programming Language :: Python :: 3.9
Classifier: Programming Language :: Python :: 3.10
Classifier: Programming Language :: Python :: 3.11
Requires-Dist: nonebot-adapter-onebot (>=2.0.0-beta.1,<3.0.0)
Requires-Dist: nonebot2 (>=2.0.0b1,<3.0.0)
